[
  {
    "ExportType": "AthenaCharacterItemDefinition",
    "ExportValue": {
      "HeroDefinition": {
        "ObjectName": "HID_971_Athena_Commando_M_Jupiter",
        "OuterIndex": {
          "ObjectName": "/Game/Athena/Heroes/HID_971_Athena_Commando_M_Jupiter",
          "OuterIndex": 0
        }
      },
      "FoleyLibraries": [
        {
          "ObjectName": "FoleyLib_Jupiter_C",
          "OuterIndex": {
            "ObjectName": "/Game/Sounds/Fort_Foley_Sounds/FoleyLibraries/Jupiter/FoleyLib_Jupiter",
            "OuterIndex": 0
          }
        }
      ],
      "ItemVariants": [
        {
          "ObjectName": "FortCosmeticMaterialVariant",
          "OuterIndex": {
            "ObjectName": "CID_971_Athena_Commando_M_Jupiter_S0Z6M",
            "OuterIndex": 0
          }
        }
      ],
      "Rarity": "EFortRarity::Epic",
      "DisplayName": {
        "Namespace": "",
        "Key": "EFCEAA1340E232052A9EA6B0083CD844",
        "SourceString": "Master Chief"
      },
      "ShortDescription": {
        "Namespace": "",
        "Key": "9658361F4EFF6B98FF153898E58C9D52",
        "SourceString": "Outfit"
      },
      "Description": {
        "Namespace": "",
        "Key": "DD29CA854C659142785AD1AF3442BC12",
        "SourceString": "Master Chief Petty Officer John-117."
      },
      "GameplayTags": [
        "Cosmetics.Filter.Season.15",
        "Cosmetics.Set.CoffinDriver",
        "Cosmetics.Source.ItemShop",
        "Cosmetics.QuestsMetaData.Outfit.Jupiter.S0Z6M"
      ],
      "Series": {
        "ObjectName": "PlatformSeries",
        "OuterIndex": {
          "ObjectName": "/Game/Athena/Items/Cosmetics/Series/PlatformSeries",
          "OuterIndex": 0
        }
      }
    }
  },
  {
    "ExportType": "FortCosmeticMaterialVariant",
    "ExportValue": {
      "MaterialOptions": [
        {
          "VariantMaterials": [],
          "VariantMaterialParams": [],
          "VariantSounds": [],
          "VariantFoley": [],
          "MetaTags": {
            "MetaTagsToApply": [],
            "MetaTagsToRemove": []
          },
          "bStartUnlocked": true,
          "bIsDefault": true,
          "bHideIfNotOwned": false,
          "CustomizationVariantTag": {
            "TagName": "Cosmetics.Variant.Property.Mat1"
          },
          "VariantName": {
            "Namespace": "",
            "Key": "BD7A384B405E8A4823C8098104822D0D",
            "SourceString": "Master Chief"
          },
          "PreviewImage": {
            "AssetPathName": "/Game/UI/Foundation/Textures/Icons/Heroes/Athena/Soldier/T-Soldier-HID-971-Athena-Commando-M-Jupiter.T-Soldier-HID-971-Athena-Commando-M-Jupiter",
            "SubPathString": null
          },
          "UnlockRequirements": null,
          "UnlockingItemDef": {
            "AssetPathName": "None",
            "SubPathString": null
          }
        },
        {
          "VariantMaterials": [
            {
              "MaterialToSwap": {
                "AssetPathName": "/Game/Characters/Player/Male/Medium/Bodies/M_MED_Jupiter/Materials/Jupiter_Body.Jupiter_Body",
                "SubPathString": null
              },
              "ComponentToOverride": null,
              "CascadeMaterialName": null,
              "MaterialOverrideIndex": 0,
              "OverrideMaterial": {
                "AssetPathName": "/Game/Characters/Player/Male/Medium/Bodies/M_MED_Jupiter/Skin/M_MED_Jupiter_Gold/Materials/Jupiter_Gold_Body.Jupiter_Gold_Body",
                "SubPathString": null
              }
            },
            {
              "MaterialToSwap": {
                "AssetPathName": "/Game/Characters/Player/Male/Medium/Bodies/M_MED_Jupiter/Materials/Jupiter_FaceAcc.Jupiter_FaceAcc",
                "SubPathString": null
              },
              "ComponentToOverride": null,
              "CascadeMaterialName": null,
              "MaterialOverrideIndex": 0,
              "OverrideMaterial": {
                "AssetPathName": "/Game/Characters/Player/Male/Medium/Bodies/M_MED_Jupiter/Skin/M_MED_Jupiter_Gold/Materials/Jupiter_Gold_FaceAcc.Jupiter_Gold_FaceAcc",
                "SubPathString": null
              }
            }
          ],
          "VariantMaterialParams": [],
          "VariantSounds": [],
          "VariantFoley": [],
          "MetaTags": {
            "MetaTagsToApply": [],
            "MetaTagsToRemove": []
          },
          "bStartUnlocked": false,
          "bIsDefault": false,
          "bHideIfNotOwned": true,
          "CustomizationVariantTag": {
            "TagName": "Cosmetics.Variant.Property.Mat2"
          },
          "VariantName": {
            "Namespace": "",
            "Key": "FBE1588846125B700B1582883E4E2A0F",
            "SourceString": "Matte Black"
          },
          "PreviewImage": {
            "AssetPathName": "/Game/UI/Foundation/Textures/Icons/Heroes/Variants/T-Variant-971-M-Jupiter-Gold.T-Variant-971-M-Jupiter-Gold",
            "SubPathString": null
          },
          "UnlockRequirements": null,
          "UnlockingItemDef": {
            "AssetPathName": "None",
            "SubPathString": null
          }
        }
      ],
      "VariantChannelTag": {
        "TagName": "Cosmetics.Variant.Channel.Material"
      },
      "VariantChannelName": {
        "Namespace": "",
        "Key": "7C06D36840CB8F39729B689D296FED6F",
        "SourceString": "Master Chief"
      }
    }
  }
]