[
  {
    "ExportType": "AthenaCharacterItemDefinition",
    "ExportValue": {
      "HeroDefinition": {
        "ObjectName": "HID_964_Athena_Commando_M_Historian",
        "OuterIndex": {
          "ObjectName": "/Game/Athena/Heroes/HID_964_Athena_Commando_M_Historian",
          "OuterIndex": 0
        }
      },
      "FoleyLibraries": [
        {
          "ObjectName": "FoleyLib_Historian_C",
          "OuterIndex": {
            "ObjectName": "/Game/Sounds/Fort_Foley_Sounds/FoleyLibraries/Historian/FoleyLib_Historian",
            "OuterIndex": 0
          }
        }
      ],
      "ItemVariants": [
        {
          "ObjectName": "FortCosmeticCharacterPartVariant",
          "OuterIndex": {
            "ObjectName": "CID_964_Athena_Commando_M_Historian_869BC",
            "OuterIndex": 0
          }
        }
      ],
      "Rarity": "EFortRarity::Epic",
      "DisplayName": {
        "Namespace": "",
        "Key": "F1FDB068453C14A025992AB6FC54543C",
        "SourceString": "Kratos"
      },
      "ShortDescription": {
        "Namespace": "",
        "Key": "9658361F4EFF6B98FF153898E58C9D52",
        "SourceString": "Outfit"
      },
      "Description": {
        "Namespace": "",
        "Key": "255976E947684EFB438AA2A57DC25494",
        "SourceString": "I am what the gods made me."
      },
      "GameplayTags": [
        "Cosmetics.Filter.Season.15",
        "Cosmetics.Set.ReformBike",
        "Cosmetics.Source.ItemShop",
        "Cosmetics.QuestsMetaData.Outfit.Historian.869BC"
      ],
      "Series": {
        "ObjectName": "PlatformSeries",
        "OuterIndex": {
          "ObjectName": "/Game/Athena/Items/Cosmetics/Series/PlatformSeries",
          "OuterIndex": 0
        }
      }
    }
  },
  {
    "ExportType": "FortCosmeticCharacterPartVariant",
    "ExportValue": {
      "PartOptions": [
        {
          "VariantParts": [],
          "VariantMaterials": [],
          "VariantMaterialParams": [],
          "InitalParticelSystemData": [],
          "VariantParticles": [],
          "VariantParticleParams": [],
          "VariantSwapInParticles": [],
          "VariantAlteredParticleParams": [],
          "VariantFoley": [],
          "SocketTransforms": [],
          "VariantActions": [],
          "MetaTags": {
            "MetaTagsToApply": [],
            "MetaTagsToRemove": []
          },
          "bStartUnlocked": true,
          "bIsDefault": true,
          "bHideIfNotOwned": false,
          "CustomizationVariantTag": {
            "TagName": "Cosmetics.Variant.Property.Stage1"
          },
          "VariantName": {
            "Namespace": "",
            "Key": "D7EB22C14234691B09FD1197337ED108",
            "SourceString": "Kratos"
          },
          "PreviewImage": {
            "AssetPathName": "/Game/UI/Foundation/Textures/Icons/Heroes/Athena/Soldier/T-Soldier-HID-964-Athena-Commando-M-Historian.T-Soldier-HID-964-Athena-Commando-M-Historian",
            "SubPathString": null
          },
          "UnlockRequirements": null,
          "UnlockingItemDef": {
            "AssetPathName": "None",
            "SubPathString": null
          }
        },
        {
          "VariantParts": [
            {
              "AssetPathName": "/Game/Athena/Heroes/Meshes/Bodies/CP_Athena_Body_M_HistorianHeavy.CP_Athena_Body_M_HistorianHeavy",
              "SubPathString": null
            }
          ],
          "VariantMaterials": [],
          "VariantMaterialParams": [],
          "InitalParticelSystemData": [],
          "VariantParticles": [],
          "VariantParticleParams": [],
          "VariantSwapInParticles": [],
          "VariantAlteredParticleParams": [],
          "VariantFoley": [],
          "SocketTransforms": [],
          "VariantActions": [],
          "MetaTags": {
            "MetaTagsToApply": [],
            "MetaTagsToRemove": []
          },
          "bStartUnlocked": false,
          "bIsDefault": false,
          "bHideIfNotOwned": true,
          "CustomizationVariantTag": {
            "TagName": "Cosmetics.Variant.Property.Stage2"
          },
          "VariantName": {
            "Namespace": "",
            "Key": "BC86DA694A492842B2BECE9194D0FF65",
            "SourceString": "Armored Kratos"
          },
          "PreviewImage": {
            "AssetPathName": "/Game/UI/Foundation/Textures/Icons/Heroes/Variants/T-Variant-964-M-Historian-Heavy.T-Variant-964-M-Historian-Heavy",
            "SubPathString": null
          },
          "UnlockRequirements": null,
          "UnlockingItemDef": {
            "AssetPathName": "None",
            "SubPathString": null
          }
        }
      ],
      "VariantChannelTag": {
        "TagName": "Cosmetics.Variant.Channel.Parts"
      },
      "VariantChannelName": {
        "Namespace": "",
        "Key": "E5A179EF421AC90C4EB098BC18B97782",
        "SourceString": "STYLE"
      }
    }
  }
]