[
  {
    "ExportType": "AthenaCharacterItemDefinition",
    "ExportValue": {
      "HeroDefinition": {
        "ObjectName": "HID_890_Athena_Commando_F_ChOneHeadhunter",
        "OuterIndex": {
          "ObjectName": "/Game/Athena/Heroes/HID_890_Athena_Commando_F_ChOneHeadhunter",
          "OuterIndex": 0
        }
      },
      "ItemVariants": [
        {
          "ObjectName": "FortCosmeticMaterialVariant",
          "OuterIndex": {
            "ObjectName": "CID_890_Athena_Commando_F_ChOneHeadhunter",
            "OuterIndex": 0
          }
        }
      ],
      "ItemVariantPreviews": [
        {
          "UnlockCondition": null,
          "PreviewTime": 3.0,
          "VariantOptions": [
            {
              "OwnedVariantTags": [],
              "ItemVariantIsUsedFor": 0,
              "CustomData": null,
              "VariantChannelTag": {
                "TagName": "Cosmetics.Variant.Channel.Material"
              },
              "ActiveVariantTag": {
                "TagName": "Cosmetics.Variant.Property.Mat2"
              }
            }
          ],
          "AdditionalItems": []
        }
      ],
      "DisplayName": {
        "Namespace": "",
        "Key": "92B6EFAC4F61297092DEE5B46136D4C9",
        "SourceString": "Headhunter Prime"
      },
      "ShortDescription": {
        "Namespace": "",
        "Key": "9658361F4EFF6B98FF153898E58C9D52",
        "SourceString": "Outfit"
      },
      "Description": {
        "Namespace": "",
        "Key": "0B212B6C4DBAD206ABEE7E9238CC21ED",
        "SourceString": "It's prime time."
      },
      "GameplayTags": [
        "Cosmetics.Source.ItemShop",
        "Cosmetics.Filter.Season.14",
        "Cosmetics.UserFacingFlags.HasVariants",
        "Cosmetics.Set.Beginnings"
      ],
      "DisplayAssetPath": {
        "AssetPathName": "/Game/Catalog/DisplayAssets/DA_Featured_CID_890_Athena_Commando_F_ChOneHeadhunter.DA_Featured_CID_890_Athena_Commando_F_ChOneHeadhunter",
        "SubPathString": null
      }
    }
  },
  {
    "ExportType": "FortCosmeticMaterialVariant",
    "ExportValue": {
      "MaterialOptions": [
        {
          "VariantMaterials": [],
          "VariantMaterialParams": [],
          "VariantSounds": [],
          "VariantFoley": [],
          "MetaTags": {
            "MetaTagsToApply": [],
            "MetaTagsToRemove": []
          },
          "bStartUnlocked": true,
          "bIsDefault": true,
          "bHideIfNotOwned": false,
          "CustomizationVariantTag": {
            "TagName": "Cosmetics.Variant.Property.Mat1"
          },
          "VariantName": {
            "Namespace": "",
            "Key": "D28B14FF463248E464ECF497FC1FB8FF",
            "SourceString": "DEFAULT"
          },
          "PreviewImage": {
            "AssetPathName": "/Game/UI/Foundation/Textures/Icons/Heroes/Athena/Soldier/T-Soldier-HID-890-Athena-Commando-F-ChOneHeadhunter.T-Soldier-HID-890-Athena-Commando-F-ChOneHeadhunter",
            "SubPathString": null
          },
          "UnlockRequirements": null,
          "UnlockingItemDef": {
            "AssetPathName": "None",
            "SubPathString": null
          }
        },
        {
          "VariantMaterials": [
            {
              "MaterialToSwap": {
                "AssetPathName": "/Game/Characters/Player/Female/Medium/Bodies/F_MED_Ch_One_Redux/Skins/Headhunter_Default/Materials/F_MED_HeadhunterDefaultRedux.F_MED_HeadhunterDefaultRedux",
                "SubPathString": null
              },
              "ComponentToOverride": null,
              "CascadeMaterialName": null,
              "MaterialOverrideIndex": 0,
              "OverrideMaterial": {
                "AssetPathName": "/Game/Characters/Player/Female/Medium/Bodies/F_MED_Ch_One_Redux/Skins/Headhunter_Camo/Materials/F_MED_HeadhunterCamoRedux.F_MED_HeadhunterCamoRedux",
                "SubPathString": null
              }
            }
          ],
          "VariantMaterialParams": [],
          "VariantSounds": [],
          "VariantFoley": [],
          "MetaTags": {
            "MetaTagsToApply": [],
            "MetaTagsToRemove": []
          },
          "bStartUnlocked": true,
          "bIsDefault": false,
          "bHideIfNotOwned": false,
          "CustomizationVariantTag": {
            "TagName": "Cosmetics.Variant.Property.Mat2"
          },
          "VariantName": {
            "Namespace": "",
            "Key": "E7B45B40458C1205A0BE26993DF44D15",
            "SourceString": "CAMO"
          },
          "PreviewImage": {
            "AssetPathName": "/Game/UI/Foundation/Textures/Icons/Heroes/Variants/T-Variant-890-F-ChOneHeadhunter-B.T-Variant-890-F-ChOneHeadhunter-B",
            "SubPathString": null
          },
          "UnlockRequirements": null,
          "UnlockingItemDef": {
            "AssetPathName": "None",
            "SubPathString": null
          }
        }
      ],
      "VariantChannelTag": {
        "TagName": "Cosmetics.Variant.Channel.Material"
      },
      "VariantChannelName": {
        "Namespace": "",
        "Key": "3DDA75D0434756658FDB1EB8F37848E2",
        "SourceString": "STYLE"
      }
    }
  }
]